[
  {
    "Id": 1,
    "SalePrice": 208500,
    "LotArea": 8450,
    "OverallQual": 7,
    "OverallCond": 5,
    "YearBuilt": 2003,
    "YearRemodAdd": 2003,
    "Neighborhood": "CollgCr",
    "HouseStyle": "2Story",
    "RoofStyle": "Gable",
    "Exterior1st": "VinylSd",
    "ExterQual": "Gd",
    "Foundation": "PConc",
    "BsmtQual": "Gd",
    "TotalBsmtSF": 856,
    "HeatingQC": "Ex",
    "CentralAir": "Y",
    "1stFlrSF": 856,
    "2ndFlrSF": 854,
    "BedroomAbvGr": 3,
    "KitchenQual": "Gd",
    "GarageCars": 2,
    "GarageArea": 548,
    "MoSold": 2,
    "YrSold": 2008
  },
  {
    "Id": 2,
    "SalePrice": 181500,
    "LotArea": 9600,
    "OverallQual": 6,
    "OverallCond": 8,
    "YearBuilt": 1976,
    "YearRemodAdd": 1976,
    "Neighborhood": "Veenker",
    "HouseStyle": "1Story",
    "RoofStyle": "Gable",
    "Exterior1st": "MetalSd",
    "ExterQual": "TA",
    "Foundation": "CBlock",
    "BsmtQual": "Gd",
    "TotalBsmtSF": 1262,
    "HeatingQC": "Ex",
    "CentralAir": "Y",
    "1stFlrSF": 1262,
    "2ndFlrSF": 0,
    "BedroomAbvGr": 3,
    "KitchenQual": "TA",
    "GarageCars": 2,
    "GarageArea": 460,
    "MoSold": 5,
    "YrSold": 2007
  },
  {
    "Id": 3,
    "SalePrice": 223500,
    "LotArea": 11250,
    "OverallQual": 7,
    "OverallCond": 5,
    "YearBuilt": 2001,
    "YearRemodAdd": 2002,
    "Neighborhood": "CollgCr",
    "HouseStyle": "2Story",
    "RoofStyle": "Gable",
    "Exterior1st": "VinylSd",
    "ExterQual": "Gd",
    "Foundation": "PConc",
    "BsmtQual": "Gd",
    "TotalBsmtSF": 920,
    "HeatingQC": "Ex",
    "CentralAir": "Y",
    "1stFlrSF": 920,
    "2ndFlrSF": 866,
    "BedroomAbvGr": 3,
    "KitchenQual": "Gd",
    "GarageCars": 2,
    "GarageArea": 608,
    "MoSold": 9,
    "YrSold": 2008
  }
]
